{
  "Code": "コード",
  "Issues": "課題",
  "Pull requests": "プルリクエスト",
  "Actions": "アクション",
  "Projects": "プロジェクト",
  "Wiki": "Wiki",
  "Security": "セキュリティ",
  "Insights": "分析",

  "New issue": "新しい課題",
  "New": "新規",
  "Billing": "請求",
  "Edit": "編集",
  "Preview": "プレビュー",
  "Delete": "削除",
  "Save": "保存",
  "Cancel": "キャンセル",
  "Close": "閉じる",
  "Open": "オープン",
  "Closed": "クローズ",
  "Search": "検索",

  "Sign in": "サインイン",
  "Sign up": "サインアップ",
  "Settings": "設定",
  "settings": "設定",
  "Notifications": "通知",
  "Integrations": "統合",

  "Appearance": "外観",
  "Accessibility": "アクセシビリティ",
  "Public profile": "公開プロフィール",
  "User settings": "ユーザー設定",
  "Account settings": "アカウント設定",

  "Account": "アカウント",
  "Access": "アクセス",
  "Billing and licensing": "請求とライセンス",
  "Emails": "メール",
  "Password and authentication": "パスワードと認証",
  "Sessions": "セッション",
  "SSH and GPG keys": "SSH/GPGキー",
  "Organizations": "組織",
  "Enterprises": "エンタープライズ",
  "Moderation": "モデレーション",
  "Code, planning, and automation": "コード、計画、オートメーション",
  "Repositories": "リポジトリ",
  "Codespaces": "Codespaces",
  "Models": "モデル",
  "Models paid usage": "Models の有料利用",
  "Packages": "パッケージ",
  "Allow Models paid usage": "Models の有料利用を許可",
  "Use models with rate limits": "レート制限付きでモデルを使用",
  "Models pricing": "モデルの料金",
  "free rate limits": "無料のレート制限",
  "You currently have": "現在、",
  ". Enable paid usage to avoid interruption and add tokens.": ". 中断を避けるために有料利用を有効にし、トークンを追加してください。",
  "If enabled, usage beyond the free tier will be billed per token based on model pricing from your Models budget.": "有効にすると、無料枠を超えた利用は Models 予算の範囲で、モデル料金に基づきトークン単位で請求されます。",
  "Copilot": "Copilot",
  "Features": "機能",
  "Pages": "Pages",
  "Saved replies": "保存済み返信",
  "Applications": "アプリケーション",
  "Scheduled reminders": "予定リマインダー",
  "Archives": "アーカイブ",
  "Developer settings": "開発者設定",
  "Security log": "セキュリティログ",
  "Sponsorship log": "スポンサーシップログ",
  "Code security": "コードセキュリティ",
  "Interaction limits": "インタラクション制限",
  "Code review limits": "コードレビュー制限",
  "Blocked users": "ブロック中のユーザー",
  "Overview": "概要",
  "Usage": "使用状況",
  "Premium request analytics": "Premiumリクエスト分析",
  "Budgets and alerts": "予算とアラート",
  "Search or jump to…": "検索または移動…",
  "Licensing": "ライセンス",
  "Payment information": "支払い情報",
  "Open global navigation menu": "グローバルナビゲーションメニューを開く",
  "Open user navigation menu": "ユーザーナビゲーションメニューを開く",
  "GitHub Homepage": "GitHub ホームページ",
  "Homepage": "ホームページ",
  "GitHub Breadcrumb": "GitHub パンくずリスト",
  "Payment history": "支払い履歴",
  "Additional billing details": "追加の請求情報",

  "Enable high contrast for light or dark mode (or both) based on your system settings": "システム設定に基づき、ライト/ダーク（または両方）でハイコントラストを有効にします",
  "Font preference for plain text editors that support Markdown styling (e.g. pull request and issue descriptions, comments.)": "Markdown の装飾に対応したプレーンテキストエディター（例：プルリクエストや Issue の説明、コメント）のフォント設定。",
  "Choose how GitHub looks to you. Select a single theme, or sync with your system and automatically switch between day and night themes. Selections are applied immediately and saved automatically.": "GitHub の見た目を選択します。単一のテーマを選ぶか、システムと同期して昼夜のテーマを自動で切り替えます。選択はすぐに反映され、自動的に保存されます。",
  "Education benefits": "教育特典",
  "Upload a photo…": "写真をアップロード…",
  "Remove photo": "写真を削除",
  "Please upload a picture smaller than 1 MB.": "1 MB 未満の画像をアップロードしてください。",
  "Please upload a picture smaller than 10,000x10,000.": "10,000x10,000 未満の画像をアップロードしてください。",
  "We only support PNG, GIF, or JPG pictures.": "PNG、GIF、JPG の画像のみ対応しています。",
  "Something went really wrong and we can’t process that picture.": "問題が発生したため、その画像を処理できません。",
  "This file is empty.": "このファイルは空です。",
  "File contents don’t match the file extension.": "ファイルの内容が拡張子と一致しません。",

  "Dark mode": "ダークモード",
  "Hometown": "出身地",
  "Light mode": "ライトモード",
  "On": "オン",
  "Off": "オフ",
  "Preview feature": "プレビュー機能",
  "Theme preferences": "テーマ設定",
  "Theme mode": "テーマモード",
  "Dark theme": "ダークテーマ",
  "URL": "URL",
  "Light theme": "ライトテーマ",
  "Selected theme:": "選択中のテーマ:",
  "Contributions & activity": "貢献とアクティビティ",
  "Include private contributions on my profile": "プロフィールに非公開の貢献を含める",
  "Make profile private and hide activity": "プロフィールを非公開にし、アクティビティを隠す",
  "Show Achievements on my profile": "プロフィールに実績を表示",
  "Your achievements will be shown on your profile.": "実績がプロフィールに表示されます。",
  "Update preference": "設定を更新",
  "Update preferences": "設定を更新",

  "Trending Repositories": "トレンドのリポジトリ",
  "Contrast": "コントラスト",
  "Increase contrast": "コントラストを上げる",


  "ORCID iD": "ORCID iD",
  "Connect your ORCID iD": "ORCID iD を連携",
  "privacy statement": "プライバシーステートメント",
  "Building an application, service, or tool that integrates with GitHub?": "GitHub と連携するアプリ、サービス、ツールを開発していますか？",
  "GitHub Developer Program": "GitHub 開発者プログラム",
  "Join the GitHub Developer Program": "GitHub 開発者プログラムに参加",
  "Label: Pro": "ラベル: Pro",
  "Pro": "PRO",
  "Markdown editor font preference": "Markdownエディターのフォント設定",
  "Use a fixed-width (monospace) font when editing Markdown": "Markdownの編集時に等幅（モノスペース）フォントを使用する",
  "Footer navigation": "フッターナビゲーション",
  "Manage cookies": "Cookie を管理",
  "Privacy": "プライバシー",
  "Terms": "利用規約",
  "Status": "ステータス",
  "Tab size preference": "タブ幅の設定",
  "Choose the number of spaces a tab is equal to when rendering code": "コード表示でタブを何スペースとして扱うか選択します",
  "Change my username": "ユーザー名を変更する",

  "Emoji skin tone preference": "絵文字スキントーン設定",

  "delete my account": "アカウントを削除する",
  "To verify, type": "確認のため、次を入力してください",
  "You'll be prompted to verify your identity before account deletion.": "アカウント削除の前に本人確認を求められます。",
  "Your username or email:": "ユーザー名またはメールアドレス：",
  "Preferred default emoji skin tone": "既定の絵文字スキントーン",
  "Neutral": "ニュートラル",
  "Light Skin Tone": "明るい肌色",
  "Medium-Light Skin Tone": "やや明るい肌色",
  "Medium Skin Tone": "標準の肌色",
  "Medium-Dark Skin Tone": "やや濃い肌色",
  "Dark Skin Tone": "濃い肌色",

  "Dark theme picker": "ダークテーマの選択",
  "Light theme picker": "ライトテーマの選択",
  "Single theme picker": "単一テーマの選択",
  "Single theme": "単一テーマ",
  "GitHub will use your selected theme": "GitHubは選択したテーマを使用します",
  "GitHub theme will match your system active settings": "GitHubテーマはシステムの設定に合わせます",
  "This theme will be active when your system is set to “dark mode”": "システムが「ダークモード」に設定されているときにこのテーマが適用されます",
  "This theme will be active when your system is set to “light mode”": "システムが「ライトモード」に設定されているときにこのテーマが適用されます",
  "Active": "有効",
  "Active Mode": "有効モード",

  "Soft dark": "ソフトダーク",
  "Dark default": "ダーク（標準）",
  "Light default": "ライト（標準）",
  "Light tritanopia": "ライト（トリタノピア）",
  "Dark tritanopia": "ダーク（トリタノピア）",
  "Light protanopia and deuteranopia": "ライト（プロタノピア/デューテラノピア）",
  "Dark protanopia and deuteranopia": "ダーク（プロタノピア/デューテラノピア）",

  "Assistive technology hints": "支援技術のヒント",
  "Save assistive technology hint preferences": "支援技術ヒントの設定を保存",
  "Enable screen reader hint": "スクリーンリーダーのヒントを有効化",
  "Disable screen reader hint": "スクリーンリーダーのヒントを無効化",
  "Add or remove instructions for how to operate complex controls.": "複雑なコントロールの操作方法に関する説明を追加/削除します。",

  "Editor settings": "エディター設定",
  "Save editor settings": "エディター設定を保存",
  "URL paste behavior": "URL貼り付けの動作",
  "Plain text": "プレーンテキスト",
  "Formatted link": "整形リンク",
  "to paste a link in the opposite way.": "逆の方法でリンクを貼り付けるには。",

  "Hovercards": "ホバーカード",
  "Show hovercards": "ホバーカードを表示",
  "Save hovercard preferences": "ホバーカード設定を保存",

  "Content": "コンテンツ",
  "Link underlines": "リンクの下線",
  "Show link underlines": "リンクの下線を表示",
  "Hide link underlines": "リンクの下線を非表示",
  "Save content preferences": "コンテンツ設定を保存",

  "Motion": "モーション",
  "Autoplay animated images": "アニメーション画像の自動再生",
  "Automatically plays animated images": "アニメーション画像を自動再生します",
  "Prevents animated images from playing automatically": "アニメーション画像の自動再生を無効にします",
  "Adopts your system preference for reduced motion": "システムの『動きを減らす』設定に従います",
  "Sync with system": "システムと同期",
  "Enabled": "有効",
  "Disabled": "無効",
  "Save motion preferences": "モーション設定を保存",

  "Keyboard shortcuts": "キーボードショートカット",
  "GitHub shortcuts": "GitHub ショートカット",
  "General": "一般",
  "Character keys": "文字キー",
  "question mark": "クエスチョンマーク",
  "Ctrl": "Ctrl",
  "shortcut to navigate notifications, or": "通知へ移動するショートカット、または",
  "to view context relevant shortcuts.": "状況に応じたショートカットを表示します。",
  "Enable GitHub shortcuts that don't use modifier keys in their activation. For example, the g n shortcut to navigate notifications, or ? to view context relevant shortcuts.": "修飾キーを使わないGitHubショートカットを有効にします。たとえば、通知に移動するには g n、関連するショートカットの一覧を見るには ? を使用します。",
  "Learn more about character key shortcuts.": "文字キーショートカットの詳細を見る。",

  "Loading": "読み込み中",
  "Reload": "再読み込み",
  "Please reload this page": "このページを再読み込みしてください",
  "There was an error while loading.": "読み込み中にエラーが発生しました。",
  "You can’t perform that action at this time.": "現在、その操作を実行できません。",
  "Uh oh!": "おっと！",
  "Dismiss alert": "アラートを閉じる",

  "Skip to content": "コンテンツへスキップ",
  "Navigation Menu": "ナビゲーションメニュー",
  "Show more breadcrumb items": "パンくず項目をもっと表示",

  "Saved searches": "保存済み検索",
  "Create saved search": "保存済み検索を作成",
  "Use saved searches to filter your results more quickly": "保存済み検索を使って検索結果をより素早く絞り込めます",
  "Search syntax tips": "検索構文のヒント",
  "To see all available qualifiers, see our": "利用可能な修飾子（qualifier）の一覧は、こちらをご覧ください：",
  "documentation": "ドキュメント",
  "Query": "クエリ",
  "Name": "名前",
  "Type": "種類",
  "0 suggestions.": "候補 0 件。",
  "Suggestions": "候補",
  "Clear": "クリア",
  "Search code, repositories, users, issues, pull requests...": "コード、リポジトリ、ユーザー、Issue、Pull request を検索…",
  "to search": "で検索",

  "@mention": "@メンション",
  "results": "件の結果",

  "Provide feedback": "フィードバックを送る",
  "Give feedback": "フィードバック",
  "Submit feedback": "フィードバックを送信",
  "We read every piece of feedback, and take your input very seriously.": "いただいたフィードバックはすべて確認し、真摯に受け止めています。",
  "Include my email address so I can be contacted": "連絡を受け取れるようにメールアドレスを含める",

  "Open in codespace": "Codespace で開く",
  "Open in github.dev": "github.dev で開く",
  "Open in a new github.dev tab": "新しい github.dev タブで開く",

  "Public": "公開",
  "Public repository": "公開リポジトリ",
  "Activity": "アクティビティ",
  "Tags": "タグ",
  "Branches": "ブランチ",
  "Watchers": "ウォッチャー",
  "Forks": "フォーク",
  "Stars": "スター",
  "watching": "ウォッチ中",
  "forks": "フォーク",
  "stars": "スター",
  "Watch": "ウォッチ",
  "Fork": "フォーク",
  "Star": "スター",
  "Starred": "スター済み",
  "Pin": "ピン留め",

  "License": "ライセンス",
  "MIT license": "MITライセンス",
  "About": "概要",
  "Resources": "リソース",
  "Readme": "README",
  "Deployments": "デプロイ",
  "Releases": "リリース",
  "No releases published": "公開済みリリースはありません",
  "No packages published": "公開済みパッケージはありません",
  "Publish your first package": "最初のパッケージを公開する",
  "Create a new release": "新しいリリースを作成",
  "Edit repository details": "リポジトリ詳細を編集",
  "Topics": "トピック",
  "Website": "Webサイト",
  "Description": "説明",
  "(separate with spaces)": "（スペースで区切ります）",
  "Include in the home page": "ホームページに表示する",

  "Repository files navigation": "リポジトリのファイルナビゲーション",
  "Repository": "リポジトリ",
  "Repository files": "リポジトリのファイル",
  "Repository details": "リポジトリの詳細",
  "See your forks of this repository": "このリポジトリのあなたのフォークを見る",
  "View all files": "すべてのファイルを表示",
  "Drop to upload your files": "ドロップしてファイルをアップロード",
  "Add file": "ファイルを追加",
  "Go to file": "ファイルへ移動",
  "Additional navigation options": "追加のナビゲーションオプション",
  "Open more actions menu": "その他の操作メニューを開く",
  "Edit file": "ファイルを編集",

  "Outline": "アウトライン",
  "Gists": "Gist",
  "Sponsors": "スポンサー",
  "Pin this repository to your profile": "このリポジトリをプロフィールにピン留め",
  "Remove topic": "トピックを削除",
  "User navigation": "ユーザーナビゲーション",

  "Suggested workflows": "おすすめのワークフロー",
  "More workflows": "他のワークフロー",
  "Publish Node.js Package": "Node.js パッケージを公開",
  "Publishes a Node.js package to npm.": "Node.js パッケージを npm に公開します。",
  "Based on your tech stack": "使用している技術スタックに基づく",

  "Go to Branches page": "ブランチ一覧へ移動",
  "Go to Tags page": "タグ一覧へ移動",
  "main branch": "main ブランチ",

  "Star this repository": "このリポジトリをスター",
  "Unstar this repository": "このリポジトリのスターを解除",
  "Star this repository (0)": "このリポジトリをスター (0)",
  "Starred, click to unstar this repository (0)": "スター済み。クリックしてこのリポジトリのスターを解除 (0)",

  "History": "履歴",
  "Latest commit": "最新のコミット",
  "Last commit date": "最終コミット日時",
  "Last commit message": "最終コミットメッセージ",
  "Folders and files": "フォルダーとファイル",
  "2 Commits": "2 コミット",

  "You have no unread notifications": "未読の通知はありません",
  "Your pull requests": "あなたのPull request",
  "Your issues": "あなたのIssue",
  "Chat with Copilot": "Copilot とチャット",
  "Coding agent": "コーディングエージェント",
  "Open agents panel": "エージェントパネルを開く",
  "New agent session": "新しいエージェントセッション",

  "You switched accounts on another tab or window.": "別のタブまたはウィンドウでアカウントを切り替えました。",
  "You signed out in another tab or window.": "別のタブまたはウィンドウでサインアウトしました。",
  "You signed in with another tab or window.": "別のタブまたはウィンドウでサインインしました。",
  "to refresh your session.": "セッションを更新するために。",

  "Enable previewing link content via mouse hover or keyboard focus before navigation. Move focus to hovercard content using": "リンク先へ移動する前に、マウスホバーまたはキーボードフォーカスでリンク内容をプレビューできます。次の操作でホバーカードの内容へフォーカスを移動します：",
  "Save keyboard shortcut preferences": "キーボードショートカット設定を保存",

  "Sign out": "サインアウト",
  "Set status": "ステータスを設定",
  "Try Enterprise": "Enterpriseを試す",
  "Upgrade": "アップグレード",
  "Home": "ホーム",
  "Profile": "プロフィール",
  "Feature preview": "機能プレビュー",
  "Copilot settings": "Copilot設定",
  "Account switcher": "アカウント切り替え",
  "Your profile": "あなたのプロフィール",
  "Your personal account": "個人アカウント",
  "Go to your personal profile": "個人プロフィールへ移動",

  "Profile picture": "プロフィール画像",
  "Social account": "ソーシャルアカウント",
  "Social accounts": "ソーシャルアカウント",
  "Public email": "公開メールアドレス",
  "Bio": "自己紹介",
  "Pronouns": "代名詞",
  "she/her": "she/her（彼女）",
  "he/him": "he/him（彼）",
  "they/them": "they/them（彼ら）",
  "Don't specify": "指定しない",
  "Custom": "カスタム",
  "Link to social profile 1": "ソーシャルプロフィールへのリンク 1",
  "Link to social profile 2": "ソーシャルプロフィールへのリンク 2",
  "Link to social profile 3": "ソーシャルプロフィールへのリンク 3",
  "Link to social profile 4": "ソーシャルプロフィールへのリンク 4",
  "Tell us a little bit about yourself": "自己紹介を入力してください",
  "Update profile": "プロフィールを更新",

  "Read more": "続きを読む",
  "Saved": "保存しました",
  "Save changes": "変更を保存",
  "Enable": "有効化",
  "Beta": "ベータ",
  "Branch": "ブランチ",
  "Docs": "ドキュメント",
  "Community": "コミュニティ",
  "Explore": "探索",
  "Configure": "設定",
  "Contact": "お問い合わせ",
  "Close dialog": "ダイアログを閉じる",
  "Close menu": "メニューを閉じる",
  "Dismiss error": "エラーを閉じる",
  "Dismiss suggestions": "候補を閉じる",
  "Do not share my personal information": "個人情報を共有しない",
  "Display PRO badge": "PROバッジを表示",
  "Available for hire": "採用可能",
  "Edit repository metadata": "リポジトリメタデータを編集",
  "Enter a new username": "新しいユーザー名を入力",
  "Enter a valid URL": "有効なURLを入力",
  "Forks could not be loaded": "フォークを読み込めませんでした",
  "0 users starred this repository": "このリポジトリをスターしたユーザーは0人です",
  "4 (Default)": "4（既定）",
  "Create new…": "新規作成…",
  "Create something new": "新しく作成",
  "Free": "無料",
  "Time zone": "タイムゾーン",
  "(GMT+00:00) UTC": "(GMT+00:00) 協定世界時（UTC）",
  "(GMT+00:00) London": "(GMT+00:00) ロンドン",
  "(GMT+01:00) Paris": "(GMT+01:00) パリ",
  "(GMT+01:00) Berlin": "(GMT+01:00) ベルリン",
  "(GMT+01:00) Madrid": "(GMT+01:00) マドリード",
  "(GMT+01:00) Rome": "(GMT+01:00) ローマ",
  "(GMT+01:00) Amsterdam": "(GMT+01:00) アムステルダム",
  "(GMT+01:00) Brussels": "(GMT+01:00) ブリュッセル",
  "(GMT+01:00) Zurich": "(GMT+01:00) チューリッヒ",
  "(GMT+01:00) Vienna": "(GMT+01:00) ウィーン",
  "(GMT+01:00) Warsaw": "(GMT+01:00) ワルシャワ",
  "(GMT+01:00) Stockholm": "(GMT+01:00) ストックホルム",
  "(GMT+01:00) Copenhagen": "(GMT+01:00) コペンハーゲン",
  "(GMT+01:00) Prague": "(GMT+01:00) プラハ",
  "(GMT+01:00) Dublin": "(GMT+01:00) ダブリン",
  "(GMT+01:00) West Central Africa": "(GMT+01:00) 西中央アフリカ",
  "(GMT+02:00) Athens": "(GMT+02:00) アテネ",
  "(GMT+02:00) Cairo": "(GMT+02:00) カイロ",
  "(GMT+02:00) Helsinki": "(GMT+02:00) ヘルシンキ",
  "(GMT+02:00) Jerusalem": "(GMT+02:00) エルサレム",
  "(GMT+02:00) Kyiv": "(GMT+02:00) キーウ",
  "(GMT+03:00) Baghdad": "(GMT+03:00) バグダッド",
  "(GMT+03:00) Istanbul": "(GMT+03:00) イスタンブール",
  "(GMT+03:00) Moscow": "(GMT+03:00) モスクワ",
  "(GMT+03:00) St. Petersburg": "(GMT+03:00) サンクトペテルブルク",
  "(GMT+03:30) Tehran": "(GMT+03:30) テヘラン",
  "(GMT+04:00) Abu Dhabi": "(GMT+04:00) アブダビ",
  "(GMT+04:00) Baku": "(GMT+04:00) バクー",
  "(GMT+04:00) Tbilisi": "(GMT+04:00) トビリシ",
  "(GMT+04:00) Yerevan": "(GMT+04:00) エレバン",
  "(GMT+04:30) Kabul": "(GMT+04:30) カブール",
  "(GMT+05:00) Islamabad": "(GMT+05:00) イスラマバード",
  "(GMT+05:00) Karachi": "(GMT+05:00) カラチ",
  "(GMT+05:45) Kathmandu": "(GMT+05:45) カトマンズ",
  "(GMT+06:00) Dhaka": "(GMT+06:00) ダッカ",
  "(GMT+07:00) Bangkok": "(GMT+07:00) バンコク",
  "(GMT+07:00) Hanoi": "(GMT+07:00) ハノイ",
  "(GMT+07:00) Jakarta": "(GMT+07:00) ジャカルタ",
  "(GMT+08:00) Beijing": "(GMT+08:00) 北京",
  "(GMT+08:00) Hong Kong": "(GMT+08:00) 香港",
  "(GMT+08:00) Singapore": "(GMT+08:00) シンガポール",
  "(GMT+08:00) Taipei": "(GMT+08:00) 台北",
  "(GMT+09:00) Seoul": "(GMT+09:00) ソウル",
  "(GMT+09:00) Tokyo": "(GMT+09:00) 東京",
  "(GMT+10:00) Sydney": "(GMT+10:00) シドニー",
  "(GMT+10:00) Melbourne": "(GMT+10:00) メルボルン",
  "(GMT+10:00) Brisbane": "(GMT+10:00) ブリスベン",
  "(GMT+11:00) Solomon Is.": "(GMT+11:00) ソロモン諸島",
  "(GMT+11:00) New Caledonia": "(GMT+11:00) ニューカレドニア",
  "(GMT+12:00) Auckland": "(GMT+12:00) オークランド",
  "(GMT+12:00) Wellington": "(GMT+12:00) ウェリントン",
  "(GMT+12:00) Marshall Is.": "(GMT+12:00) マーシャル諸島",
  "(GMT+12:45) Chatham Is.": "(GMT+12:45) チャタム諸島",
  "(GMT+13:00) Samoa": "(GMT+13:00) サモア",
  "(GMT+13:00) Tokelau Is.": "(GMT+13:00) トケラウ諸島",
  "(GMT-01:00) Azores": "(GMT-01:00) アゾレス諸島",
  "(GMT-01:00) Cape Verde Is.": "(GMT-01:00) カーボベルデ諸島",
  "(GMT-02:00) Mid-Atlantic": "(GMT-02:00) 中央大西洋",
  "(GMT-04:00) Atlantic Time (Canada)": "(GMT-04:00) 大西洋標準時（カナダ）",
  "(GMT-04:00) Puerto Rico": "(GMT-04:00) プエルトリコ",
  "(GMT-05:00) Eastern Time (US & Canada)": "(GMT-05:00) 東部標準時（米国・カナダ）",
  "(GMT-05:00) Indiana (East)": "(GMT-05:00) インディアナ（東部）",
  "(GMT-06:00) Central America": "(GMT-06:00) 中央アメリカ",
  "(GMT-06:00) Central Time (US & Canada)": "(GMT-06:00) 中部標準時（米国・カナダ）",
  "(GMT-07:00) Mountain Time (US & Canada)": "(GMT-07:00) 山岳部標準時（米国・カナダ）",
  "(GMT-08:00) Pacific Time (US & Canada)": "(GMT-08:00) 太平洋標準時（米国・カナダ）",
  "(GMT-09:00) Alaska": "(GMT-09:00) アラスカ",
  "(GMT-10:00) Hawaii": "(GMT-10:00) ハワイ",
  "(GMT-11:00) American Samoa": "(GMT-11:00) 米領サモア",
  "(GMT-11:00) Midway Island": "(GMT-11:00) ミッドウェー島",
  "(GMT-12:00) International Date Line West": "(GMT-12:00) 国際日付変更線（西側）",
  "Display current local time": "現在の現地時間を表示",
  "Location": "所在地",
  "Company": "会社",

  "Profile settings": "プロフィール設定",
  "Jobs profile": "求人プロフィール",
  "Save jobs profile": "求人プロフィールを保存",
  "Trending settings": "トレンド設定",
  "Preferred spoken language": "希望する表示言語",
  "Languages": "言語",
  "No Preference": "指定なし",

  "Enabling this will hide your contributions and activity from your GitHub profile and from social features like followers, stars, feeds, leaderboards and releases.": "これを有効にすると、GitHub プロフィールから貢献やアクティビティが非表示になり、フォロワー/スター/フィード/リーダーボード/リリースなどのソーシャル機能にも表示されなくなります。",
  "Your contribution graph, achievements, and activity overview will show your private contributions without revealing any repository or organization information.": "貢献グラフ、実績、アクティビティ概要には、リポジトリや組織の情報を公開せずに非公開の貢献が表示されます。",
  "Your name may appear around GitHub where you contribute or are mentioned. You can remove it at any time.": "あなたの名前は、貢献した場所やメンションされた場所など GitHub 上で表示されることがあります。いつでも削除できます。",

  "GitHub developer program": "GitHub開発者プログラム",
  "Footer": "フッター",
  "Lists": "リスト",
  "Initial commit": "初回コミット",
  "FREE": "無料",

  "Select a verified email to display": "表示する確認済みメールアドレスを選択",
  "You have set your email address to private. To toggle email privacy, go to": "メールアドレスを非公開に設定しています。公開/非公開を切り替えるには次へ移動してください：",
  "email settings": "メール設定",
  "Keep my email address private": "メールアドレスを非公開にする",
  "and uncheck \"Keep my email address private.\"": "そして「メールアドレスを非公開にする」のチェックを外してください。",
  "Other users will see the time difference from their local time.": "他のユーザーには、現地時間との差が表示されます。",

  "Changing your username can have": "ユーザー名の変更は",
  "unintended side effects": "予期しない影響を及ぼす可能性があります",
  "Renaming may take a few minutes to complete.": "名前の変更が完了するまで数分かかることがあります。",
  "exactly as it appears:": "表示どおりに：",
  "Looking to manage account security settings? You can find them in the": "アカウントのセキュリティ設定を管理しますか？ 次で確認できます：",
  "Deleting your user account": "ユーザーアカウントの削除",
  "designated below": "以下に指定",
  "downgrade your account": "アカウントをダウングレード",
  ". Exports will be available for 7 days.": ". エクスポートは 7 日間利用できます。",
  "Connect a Patreon account for": "Patreon アカウントを連携して",
  "For more help, read our article \"": "詳しくは次の記事をご覧ください：\"",
  "immediately delete all of your repositories (17)": "すべてのリポジトリを直ちに削除します（17）",
  "This will display the": "次が表示されます：",
  "badge on your public profile page.": "公開プロフィールページにバッジが表示されます。",
  "other users and organizations to link to them.": "他のユーザーや組織がリンクできるようにします。",
  "your company’s GitHub organization to link it.": "会社の GitHub 組織をリンクするために。",
  ", along with all of your forks, wikis, issues, pull requests, and GitHub Pages sites.": "、あなたのフォーク、Wiki、Issue、プルリクエスト、GitHub Pages サイトも含めて。",
  "You will no longer be billed, and after 90 days your username will be available to anyone on GitHub.": "これ以上請求されなくなり、90 日後にはあなたのユーザー名が GitHub 上の誰でも利用できるようになります。",

  "Delete account": "アカウントを削除",
  "Export account data": "アカウントデータをエクスポート",
  "Link Patreon account": "Patreonアカウントをリンク",
  "Connect with Patreon": "Patreonに接続",
  "Change username": "ユーザー名を変更",
  "Designate Successor": "後継者を指定",
  "Renaming may take a few minutes to complete.": "名前の変更が完了するまで数分かかる場合があります。",
  "Add Successor": "後継者を追加",
  "Successor settings": "後継者設定",
  "Search by username, full name, or email address": "ユーザー名、氏名、またはメールアドレスで検索",
  "Learn more about account successors.": "アカウント後継者について詳しく見る",
  "Cancel plan and delete this account": "プランをキャンセルしてこのアカウントを削除",
  "Delete your account": "アカウントを削除",
  "Are you sure you want to do this?": "本当に実行しますか？",
  "Really change your username?": "本当にユーザー名を変更しますか？",
  "This is extremely important.": "これは非常に重要です。",
  "Unexpected bad things will happen if you don’t read this!": "これを読まないと予期しない問題が起こる可能性があります！",
  "Once you delete your account, there is no going back. Please be certain.": "一度アカウントを削除すると元に戻せません。慎重に判断してください。",

  "Copied!": "コピーしました！"
}
